ones/__init__.py
ones/test.py
ones-0.4.0.dist-info/DESCRIPTION.rst
ones-0.4.0.dist-info/METADATA
ones-0.4.0.dist-info/RECORD
ones-0.4.0.dist-info/WHEEL
ones-0.4.0.dist-info/metadata.json
ones-0.4.0.dist-info/top_level.txt
